{
    "projects": [
        {   
            "year":"2023",
            "name":"GitHub Universe23",
            "category":"Web design",
            "type":"In-house",
            "image":"link",
            "description":"Lorem",
            "link":"https://github.com/AsianZesus?tab=repositories",
            "linklabel":"Live site"
        },
        {
            "year":"2023",
            "name":"Lorem",
            "category":"Lorem",
            "type": "In-House",
            "image": "link",
            "description": "Lorem",
            "link":"https://github.com/AsianZesus?tab=repositories",
            "linklabel": "Live Site might not need this" 
        }
    ]
}